odoo/addons/beesdoo_pos_reporting/README.rst
odoo/addons/beesdoo_pos_reporting/__init__.py
odoo/addons/beesdoo_pos_reporting/__manifest__.py
odoo/addons/beesdoo_pos_reporting/models/__init__.py
odoo/addons/beesdoo_pos_reporting/models/res_partner.py
odoo/addons/beesdoo_pos_reporting/readme/CONTRIBUTORS.rst
odoo/addons/beesdoo_pos_reporting/readme/DESCRIPTION.rst
odoo/addons/beesdoo_pos_reporting/static/description/index.html
odoo12_addon_beesdoo_pos_reporting-12.0.1.0.0.99.dev4.dist-info/METADATA
odoo12_addon_beesdoo_pos_reporting-12.0.1.0.0.99.dev4.dist-info/WHEEL
odoo12_addon_beesdoo_pos_reporting-12.0.1.0.0.99.dev4.dist-info/top_level.txt
odoo12_addon_beesdoo_pos_reporting-12.0.1.0.0.99.dev4.dist-info/RECORD
